idl/BasicDataType.idl
idl/ComponentObserver.idl
idl/DataPort.idl
idl/ExtendedDataTypes.idl
idl/ExtendedFsmService.idl
idl/InterfaceDataTypes.idl
idl/Logger.idl
idl/Manager.idl
idl/OpenRTM.idl
idl/RTC.idl
idl/SDOPackage.idl
rtctree/__init__.py
rtctree/component.py
rtctree/config_set.py
rtctree/directory.py
rtctree/exceptions.py
rtctree/exec_context.py
rtctree/manager.py
rtctree/nameserver.py
rtctree/node.py
rtctree/options.py
rtctree/path.py
rtctree/ports.py
rtctree/sdo.py
rtctree/tree.py
rtctree/unknown.py
rtctree/utils.py
rtctree/zombie.py
rtctree/data/__init__.py
rtctree/data/idl/BasicDataType.idl
rtctree/data/idl/ComponentObserver.idl
rtctree/data/idl/DataPort.idl
rtctree/data/idl/ExtendedDataTypes.idl
rtctree/data/idl/ExtendedFsmService.idl
rtctree/data/idl/InterfaceDataTypes.idl
rtctree/data/idl/Logger.idl
rtctree/data/idl/Manager.idl
rtctree/data/idl/OpenRTM.idl
rtctree/data/idl/RTC.idl
rtctree/data/idl/SDOPackage.idl
rtctree/rtc/BasicDataType_idl.py
rtctree/rtc/ComponentObserver_idl.py
rtctree/rtc/DataPort_idl.py
rtctree/rtc/ExtendedDataTypes_idl.py
rtctree/rtc/ExtendedFsmService_idl.py
rtctree/rtc/InterfaceDataTypes_idl.py
rtctree/rtc/Logger_idl.py
rtctree/rtc/Manager_idl.py
rtctree/rtc/OpenRTM_idl.py
rtctree/rtc/RTC_idl.py
rtctree/rtc/SDOPackage_idl.py
rtctree/rtc/__init__.py
rtctree/rtc/OpenRTM/__init__.py
rtctree/rtc/OpenRTM__POA/__init__.py
rtctree/rtc/RTC/__init__.py
rtctree/rtc/RTC__POA/__init__.py
rtctree/rtc/RTM/__init__.py
rtctree/rtc/RTM__POA/__init__.py
rtctree/rtc/SDOPackage/__init__.py
rtctree/rtc/SDOPackage__POA/__init__.py
test/c1_comp.py
test/c2_comp.py
test/test_idl.py
test/MyData/__init__.py
test/MyData__POA/__init__.py
rtctree_aist_test-4.2.5.dist-info/METADATA
rtctree_aist_test-4.2.5.dist-info/WHEEL
rtctree_aist_test-4.2.5.dist-info/top_level.txt
rtctree_aist_test-4.2.5.dist-info/RECORD
