Metadata-Version: 2.4
Name: rtctree-aist-test
Version: 4.2.5
Summary: API for interacting with running RT Components and managing RTM-based systems.
Author-email: Geoffrey Biggs <openrtm@openrtm.org>
License: LGPL3
Project-URL: Source, https://github.com/OpenRTM/rtctree
Classifier: Development Status :: 5 - Production/Stable
Classifier: Intended Audience :: Developers
Classifier: Natural Language :: English
Classifier: Operating System :: OS Independent
Classifier: Topic :: Software Development
Requires-Python: >=3.9
